milbi/__init__.py
milbi/__main__.py
milbi/class_config.py
milbi/class_milbi.py
milbi/class_state.py
milbi-1.0.0.dist-info/LICENSE.txt
milbi-1.0.0.dist-info/METADATA
milbi-1.0.0.dist-info/WHEEL
milbi-1.0.0.dist-info/entry_points.txt
milbi-1.0.0.dist-info/top_level.txt
milbi-1.0.0.dist-info/RECORD
